sl_git_hooks/.gitignore
sl_git_hooks/__init__.py
sl_git_hooks/__main__.py
sl_git_hooks/config.py
sl_git_hooks/configs/.gitkeep
sl_git_hooks/configs/0db4748fd0a3f8892619b247a0d98c9ca58ea698.ini
sl_git_hooks/hooks/__init__.py
sl_git_hooks/hooks/pre_commit.py
sl_git_hooks/poetry.lock
sl_git_hooks/templates/pre-commit.sh
sl_git_hooks/utils.py
sl_git_hooks-0.1.1105.dist-info/entry_points.txt
sl_git_hooks-0.1.1105.dist-info/WHEEL
sl_git_hooks-0.1.1105.dist-info/METADATA
sl_git_hooks-0.1.1105.dist-info/RECORD
