Metadata-Version: 2.1
Name: sl-git-hooks
Version: 0.1.1105
Summary: 
Author: Alexander Memer
Author-email: mkoaleksedos@gmail.com
Requires-Python: >=3.6,<4.0
Classifier: Programming Language :: Python :: 3
Classifier: Programming Language :: Python :: 3.6
Classifier: Programming Language :: Python :: 3.7
Classifier: Programming Language :: Python :: 3.8
Classifier: Programming Language :: Python :: 3.9
Requires-Dist: pygit2 (>=1.5.0,<2.0.0)
